README.md
setup.cfg
setup.py
csv_to_tmx/__init__.py
csv_to_tmx.egg-info/PKG-INFO
csv_to_tmx.egg-info/SOURCES.txt
csv_to_tmx.egg-info/dependency_links.txt
csv_to_tmx.egg-info/top_level.txt